django_elasticsearch_model_binder/__init__.py
django_elasticsearch_model_binder/exceptions.py
django_elasticsearch_model_binder/mixins.py
django_elasticsearch_model_binder/models.py
django_elasticsearch_model_binder/utils.py
django_elasticsearch_model_binder-0.1.1.dist-info/LICENSE
django_elasticsearch_model_binder-0.1.1.dist-info/METADATA
django_elasticsearch_model_binder-0.1.1.dist-info/WHEEL
django_elasticsearch_model_binder-0.1.1.dist-info/top_level.txt
django_elasticsearch_model_binder-0.1.1.dist-info/RECORD
