Metadata-Version: 2.1
Name: django-elasticsearch-model-binder
Version: 0.1.1
Summary: UNKNOWN
Home-page: https://github.com/cr0mbly/django-elasticsearch-model-binder
Author: Aidan Houlihan
Author-email: aidandhoulihan@gmail.com
License: MIT License
Platform: UNKNOWN
Classifier: Environment :: Web Environment
Classifier: Framework :: Django
Classifier: Intended Audience :: Developers
Classifier: License :: OSI Approved :: BSD License
Classifier: Operating System :: OS Independent
Classifier: Programming Language :: Python
Classifier: Programming Language :: Python :: 3.6
Classifier: Programming Language :: Python :: 3.7
Classifier: Programming Language :: Python :: 3.8
Classifier: Topic :: Internet :: WWW/HTTP
Classifier: Topic :: Internet :: WWW/HTTP :: Dynamic Content
Requires-Dist: django
Requires-Dist: elasticsearch
